<Properties>
  <MonoDevelop.Ide.Workbench ActiveDocument="../60-sec-version-2018-10-03_-_Inspirational_Advertising_1_-_David_Fesliyan.mp3">
    <Files>
      <File FileName="Assets/Script/ARAP/ARAPControl.cs" Line="87" Column="1" />
      <File FileName="Assets/Script/PlaneBuilder.cs" />
      <File FileName="Assets/Script/ARAP/ARAPOperation.cs" />
      <File FileName="Assets/Script/ARAP/ARAPTriangle.cs" Line="73" Column="30" />
      <File FileName="Assets/Script/LBS/boneWeig.cs" Line="127" Column="30" />
      <File FileName="Assets/Script/LBS/LBSBone.cs" Line="19" Column="6" />
      <File FileName="../60-sec-version-2018-10-03_-_Inspirational_Advertising_1_-_David_Fesliyan.mp3" />
    </Files>
    <Pads>
      <Pad Id="ProjectPad">
        <State name="__root__">
          <Node name="Assembly-CSharp" expanded="True">
            <Node name="Assembly-CSharp" expanded="True">
              <Node name="Assets" expanded="True">
                <Node name="Script" expanded="True">
                  <Node name="ARAP" expanded="True" />
                  <Node name="LBS" expanded="True">
                    <Node name="LBSBone.cs" selected="True" />
                  </Node>
                </Node>
              </Node>
            </Node>
          </Node>
        </State>
      </Pad>
    </Pads>
  </MonoDevelop.Ide.Workbench>
  <MonoDevelop.Ide.DebuggingService.PinnedWatches />
  <MonoDevelop.Ide.Workspace ActiveConfiguration="Debug" />
  <MonoDevelop.Ide.DebuggingService.Breakpoints>
    <BreakpointStore />
  </MonoDevelop.Ide.DebuggingService.Breakpoints>
  <MultiItemStartupConfigurations />
</Properties>